{"list": [{"股票代號": "1722.TW", "價格": 48.7, "漲幅": "3.4%", "成交量": 20004, "型態": "六線糾結", "時間": "15:02"}, {"股票代號": "1735.TW", "價格": 28.75, "漲幅": "6.68%", "成交量": 2433, "型態": "三線糾結", "時間": "15:02"}, {"股票代號": "2030.TW", "價格": 16.4, "漲幅": "1.86%", "成交量": 1189, "型態": "五線糾結", "時間": "15:02"}, {"股票代號": "2351.TW", "價格": 152.0, "漲幅": "3.4%", "成交量": 10627, "型態": "五線多排", "時間": "15:02"}, {"股票代號": "2393.TW", "價格": 71.3, "漲幅": "3.03%", "成交量": 3159, "型態": "三線糾結", "時間": "15:02"}, {"股票代號": "2882.TW", "價格": 78.6, "漲幅": "3.56%", "成交量": 71322, "型態": "五線糾結", "時間": "15:02"}, {"股票代號": "3003.TW", "價格": 55.5, "漲幅": "4.72%", "成交量": 661, "型態": "三線糾結", "時間": "15:02"}, {"股票代號": "3591.TW", "價格": 23.4, "漲幅": "2.63%", "成交量": 4569, "型態": "三線糾結", "時間": "15:03"}, {"股票代號": "3669.TW", "價格": 39.05, "漲幅": "4.41%", "成交量": 348, "型態": "三線糾結", "時間": "15:03"}, {"股票代號": "4722.TW", "價格": 186.5, "漲幅": "2.47%", "成交量": 1496, "型態": "四線糾結", "時間": "15:03"}, {"股票代號": "6706.TW", "價格": 147.0, "漲幅": "3.52%", "成交量": 9119, "型態": "三線糾結", "時間": "15:03"}, {"股票代號": "8215.TW", "價格": 26.05, "漲幅": "1.76%", "成交量": 1567, "型態": "三線糾結", "時間": "15:03"}, {"股票代號": "3567.TWO", "價格": 28.0, "漲幅": "3.32%", "成交量": 542, "型態": "六線糾結", "時間": "15:03"}, {"股票代號": "5011.TWO", "價格": 14.1, "漲幅": "2.17%", "成交量": 228, "型態": "四線糾結", "時間": "15:03"}, {"股票代號": "5410.TWO", "價格": 33.35, "漲幅": "3.57%", "成交量": 583, "型態": "六線糾結", "時間": "15:03"}, {"股票代號": "5493.TWO", "價格": 90.0, "漲幅": "4.53%", "成交量": 424, "型態": "六線糾結", "時間": "15:03"}, {"股票代號": "6151.TWO", "價格": 36.4, "漲幅": "4.15%", "成交量": 487, "型態": "三線糾結", "時間": "15:03"}, {"股票代號": "6996.TWO", "價格": 177.0, "漲幅": "2.02%", "成交量": 143, "型態": "三線糾結", "時間": "15:03"}, {"股票代號": "8068.TWO", "價格": 23.45, "漲幅": "2.18%", "成交量": 401, "型態": "五線糾結", "時間": "15:03"}], "last_slot": "0429_15:00", "ts": 1777446193.6459732}